sider__exttest.py
sider/__init__.py
sider/datetime.py
sider/exceptions.py
sider/hash.py
sider/lazyimport.py
sider/list.py
sider/session.py
sider/set.py
sider/sortedset.py
sider/threadlocal.py
sider/transaction.py
sider/types.py
sider/utils.py
sider/version.py
sider/warnings.py
sider/ext/__init__.py
Sider-0.3.1.dist-info/DESCRIPTION.rst
Sider-0.3.1.dist-info/METADATA
Sider-0.3.1.dist-info/metadata.json
Sider-0.3.1.dist-info/RECORD
Sider-0.3.1.dist-info/top_level.txt
Sider-0.3.1.dist-info/WHEEL
sidertests/__init__.py
sidertests/counter_recipe.py
sidertests/env.py
sidertests/test_hash.py
sidertests/test_list.py
sidertests/test_session.py
sidertests/test_set.py
sidertests/test_sider.py
sidertests/test_sortedset.py
sidertests/test_threadlocal.py
sidertests/test_transaction.py
sidertests/test_types.py
sidertests/test_utils.py
