Metadata-Version: 2.0
Name: Sider
Version: 0.3.1
Summary: A persistent object library based on Redis
Home-page: http://sider.dahlia.kr/
Author: Hong Minhee
Author-email: minhee@dahlia.kr
License: MIT License
Platform: UNKNOWN
Classifier: Development Status :: 3 - Alpha
Classifier: Intended Audience :: Developers
Classifier: License :: OSI Approved :: MIT License
Classifier: Operating System :: OS Independent
Classifier: Programming Language :: Python :: 2.6
Classifier: Programming Language :: Python :: 2.7
Classifier: Programming Language :: Python :: 3.3
Classifier: Programming Language :: Python :: 3.4
Classifier: Programming Language :: Python :: Implementation :: CPython
Classifier: Programming Language :: Python :: Implementation :: PyPy
Classifier: Programming Language :: Python :: Implementation :: Stackless
Classifier: Topic :: Database
Requires-Dist: redis
Provides-Extra: docs
Requires-Dist: Sphinx (>=1.1); extra == 'docs'
